{
    "mainCourse": {
        "base": {
            "baseCost": 1.1,
            "baseDescription": "a single cheese toasty"
        },
        "extras": [
            {
                "name": "Salami",
                "cost": 0.2
            },
            {
                "name": "Spring onions",
                "cost": 0.15
            },
            {
                "name": "Hot sauce",
                "cost": 0.15
            },
            {
                "name": "Herbs",
                "cost": 0.05
            }
        ]
    },

    "drinks": {
        "base": {
            "baseCost": -1,
            "baseDescription": ""
        },
        "extras": [
            {
                "name": "Diet coke (can)",
                "cost": 1.0
            },
            {
                "name": "Coffee (americo)",
                "cost": 1.20
            }
        ]
    },

    "desert": {
        "base": {
            "baseCost": 2.5,
            "baseDescription": "a plain waffle"
        },
        "extras": [
            {
                "name": "Syrup",
                "cost": 0.5
            },
            {
                "name": "Banana",
                "cost": 0.3
            },
            {
                "name": "Sugar",
                "cost": 0.1
            }
        ]
    }
}